[
  [
    {
      "header": "سُورَةُ العَصۡرِ"
    },
    {
      "ayah": "بِسْمِ ٱللَّهِ ٱلرَّحْمَٰنِ ٱلرَّحِيمِ وَٱلْعَصْرِ ﴿١﴾ إِنَّ ٱلْإِنسَٰنَ لَفِى خُسْرٍ ﴿٢﴾ إِلَّا ٱلَّذِينَ ءَامَنُوا۟ وَعَمِلُوا۟ ٱلصَّٰلِحَٰتِ وَتَوَاصَوْا۟ بِٱلْحَقِّ وَتَوَاصَوْا۟ بِٱلصَّبْرِ ﴿٣﴾ "
    },
    {
      "header": "سُورَةُ الهُمَزَةِ"
    },
    {
      "ayah": "إِلَّا ٱلَّذِينَ ءَامَنُوا۟ وَعَمِلُوا۟ ٱلصَّٰلِحَٰتِ وَتَوَاصَوْا۟ بِٱلْحَقِّ وَتَوَاصَوْا۟ بِٱلصَّبْرِ ﴿٣﴾ بِسْمِ ٱللَّهِ ٱلرَّحْمَٰنِ ٱلرَّحِيمِ وَيْلٌۭ لِّكُلِّ هُمَزَةٍۢ لُّمَزَةٍ ﴿١﴾ ٱلَّذِى جَمَعَ مَالًۭا وَعَدَّدَهُۥ ﴿٢﴾ يَحْسَبُ أَنَّ مَالَهُۥٓ أَخْلَدَهُۥ ﴿٣﴾ كَلَّا ۖ لَيُنۢبَذَنَّ فِى ٱلْحُطَمَةِ ﴿٤﴾ وَمَآ أَدْرَىٰكَ مَا ٱلْحُطَمَةُ ﴿٥﴾ نَارُ ٱللَّهِ ٱلْمُوقَدَةُ ﴿٦﴾ ٱلَّتِى تَطَّلِعُ عَلَى ٱلْأَفْـِٔدَةِ ﴿٧﴾ إِنَّهَا عَلَيْهِم مُّؤْصَدَةٌۭ ﴿٨﴾ فِى عَمَدٍۢ مُّمَدَّدَةٍۭ ﴿٩﴾ "
    },
    {
      "header": "سُورَةُ الفِيلِ"
    },
    {
      "ayah": "فِى عَمَدٍۢ مُّمَدَّدَةٍۭ ﴿٩﴾ بِسْمِ ٱللَّهِ ٱلرَّحْمَٰنِ ٱلرَّحِيمِ أَلَمْ تَرَ كَيْفَ فَعَلَ رَبُّكَ بِأَصْحَٰبِ ٱلْفِيلِ ﴿١﴾ أَلَمْ يَجْعَلْ كَيْدَهُمْ فِى تَضْلِيلٍۢ ﴿٢﴾ وَأَرْسَلَ عَلَيْهِمْ طَيْرًا أَبَابِيلَ ﴿٣﴾ تَرْمِيهِم بِحِجَارَةٍۢ مِّن سِجِّيلٍۢ ﴿٤﴾ فَجَعَلَهُمْ كَعَصْفٍۢ مَّأْكُولٍۭ ﴿٥﴾ "
    }
  ],
  [
    {
      "header": "سُورَةُ قُرَيۡشٍ"
    },
    {
      "ayah": "بِسْمِ ٱللَّهِ ٱلرَّحْمَٰنِ ٱلرَّحِيمِ لِإِيلَٰفِ قُرَيْشٍ ﴿١﴾ إِۦلَٰفِهِمْ رِحْلَةَ ٱلشِّتَآءِ وَٱلصَّيْفِ ﴿٢﴾ فَلْيَعْبُدُوا۟ رَبَّ هَٰذَا ٱلْبَيْتِ ﴿٣﴾ ٱلَّذِىٓ أَطْعَمَهُم مِّن جُوعٍۢ وَءَامَنَهُم مِّنْ خَوْفٍۭ ﴿٤﴾ "
    },
    {
      "header": "سُورَةُ المَاعُونِ"
    },
    {
      "ayah": "ٱلَّذِىٓ أَطْعَمَهُم مِّن جُوعٍۢ وَءَامَنَهُم مِّنْ خَوْفٍۭ ﴿٤﴾ بِسْمِ ٱللَّهِ ٱلرَّحْمَٰنِ ٱلرَّحِيمِ أَرَءَيْتَ ٱلَّذِى يُكَذِّبُ بِٱلدِّينِ ﴿١﴾ فَذَٰلِكَ ٱلَّذِى يَدُعُّ ٱلْيَتِيمَ ﴿٢﴾ وَلَا يَحُضُّ عَلَىٰ طَعَامِ ٱلْمِسْكِينِ ﴿٣﴾ فَوَيْلٌۭ لِّلْمُصَلِّينَ ﴿٤﴾ ٱلَّذِينَ هُمْ عَن صَلَاتِهِمْ سَاهُونَ ﴿٥﴾ ٱلَّذِينَ هُمْ يُرَآءُونَ ﴿٦﴾ وَيَمْنَعُونَ ٱلْمَاعُونَ ﴿٧﴾ "
    },
    {
      "header": "سُورَةُ الكَوۡثَرِ"
    },
    {
      "ayah": "وَيَمْنَعُونَ ٱلْمَاعُونَ ﴿٧﴾ بِسْمِ ٱللَّهِ ٱلرَّحْمَٰنِ ٱلرَّحِيمِ إِنَّآ أَعْطَيْنَٰكَ ٱلْكَوْثَرَ ﴿١﴾ فَصَلِّ لِرَبِّكَ وَٱنْحَرْ ﴿٢﴾ إِنَّ شَانِئَكَ هُوَ ٱلْأَبْتَرُ ﴿٣﴾ "
    }
  ],
  [
    {
      "header": "سُورَةُ الكَافِرُونَ"
    },
    {
      "ayah": "بِسْمِ ٱللَّهِ ٱلرَّحْمَٰنِ ٱلرَّحِيمِ قُلْ يَٰٓأَيُّهَا ٱلْكَٰفِرُونَ ﴿١﴾ لَآ أَعْبُدُ مَا تَعْبُدُونَ ﴿٢﴾ وَلَآ أَنتُمْ عَٰبِدُونَ مَآ أَعْبُدُ ﴿٣﴾ وَلَآ أَنَا۠ عَابِدٌۭ مَّا عَبَدتُّمْ ﴿٤﴾ وَلَآ أَنتُمْ عَٰبِدُونَ مَآ أَعْبُدُ ﴿٥﴾ لَكُمْ دِينُكُمْ وَلِىَ دِينِ ﴿٦﴾ "
    },
    {
      "header": "سُورَةُ النَّصۡرِ"
    },
    {
      "ayah": "لَكُمْ دِينُكُمْ وَلِىَ دِينِ ﴿٦﴾ بِسْمِ ٱللَّهِ ٱلرَّحْمَٰنِ ٱلرَّحِيمِ إِذَا جَآءَ نَصْرُ ٱللَّهِ وَٱلْفَتْحُ ﴿١﴾ وَرَأَيْتَ ٱلنَّاسَ يَدْخُلُونَ فِى دِينِ ٱللَّهِ أَفْوَاجًۭا ﴿٢﴾ فَسَبِّحْ بِحَمْدِ رَبِّكَ وَٱسْتَغْفِرْهُ ۚ إِنَّهُۥ كَانَ تَوَّابًۢا ﴿٣﴾ "
    },
    {
      "header": "سُورَةُ المَسَدِ"
    },
    {
      "ayah": "فَسَبِّحْ بِحَمْدِ رَبِّكَ وَٱسْتَغْفِرْهُ ۚ إِنَّهُۥ كَانَ تَوَّابًۢا ﴿٣﴾ بِسْمِ ٱللَّهِ ٱلرَّحْمَٰنِ ٱلرَّحِيمِ تَبَّتْ يَدَآ أَبِى لَهَبٍۢ وَتَبَّ ﴿١﴾ مَآ أَغْنَىٰ عَنْهُ مَالُهُۥ وَمَا كَسَبَ ﴿٢﴾ سَيَصْلَىٰ نَارًۭا ذَاتَ لَهَبٍۢ ﴿٣﴾ وَٱمْرَأَتُهُۥ حَمَّالَةَ ٱلْحَطَبِ ﴿٤﴾ فِى جِيدِهَا حَبْلٌۭ مِّن مَّسَدٍۭ ﴿٥﴾ "
    }
  ],
  [
    {
      "header": "سُورَةُ الإِخۡلَاصِ"
    },
    {
      "ayah": "بِسْمِ ٱللَّهِ ٱلرَّحْمَٰنِ ٱلرَّحِيمِ قُلْ هُوَ ٱللَّهُ أَحَدٌ ﴿١﴾ ٱللَّهُ ٱلصَّمَدُ ﴿٢﴾ لَمْ يَلِدْ وَلَمْ يُولَدْ ﴿٣﴾ وَلَمْ يَكُن لَّهُۥ كُفُوًا أَحَدٌۢ ﴿٤﴾ "
    },
    {
      "header": "سُورَةُ الفَلَقِ"
    },
    {
      "ayah": "وَلَمْ يَكُن لَّهُۥ كُفُوًا أَحَدٌۢ ﴿٤﴾ بِسْمِ ٱللَّهِ ٱلرَّحْمَٰنِ ٱلرَّحِيمِ قُلْ أَعُوذُ بِرَبِّ ٱلْفَلَقِ ﴿١﴾ مِن شَرِّ مَا خَلَقَ ﴿٢﴾ وَمِن شَرِّ غَاسِقٍ إِذَا وَقَبَ ﴿٣﴾ وَمِن شَرِّ ٱلنَّفَّٰثَٰتِ فِى ٱلْعُقَدِ ﴿٤﴾ وَمِن شَرِّ حَاسِدٍ إِذَا حَسَدَ ﴿٥﴾ "
    },
    {
      "header": "سُورَةُ النَّاسِ"
    },
    {
      "ayah": "وَمِن شَرِّ حَاسِدٍ إِذَا حَسَدَ ﴿٥﴾ بِسْمِ ٱللَّهِ ٱلرَّحْمَٰنِ ٱلرَّحِيمِ قُلْ أَعُوذُ بِرَبِّ ٱلنَّاسِ ﴿١﴾ مَلِكِ ٱلنَّاسِ ﴿٢﴾ إِلَٰهِ ٱلنَّاسِ ﴿٣﴾ مِن شَرِّ ٱلْوَسْوَاسِ ٱلْخَنَّاسِ ﴿٤﴾ ٱلَّذِى يُوَسْوِسُ فِى صُدُورِ ٱلنَّاسِ ﴿٥﴾ مِنَ ٱلْجِنَّةِ وَٱلنَّاسِ ﴿٦﴾ "
    }
  ]
]

